cerc_costs-0.1.0.6.data/data/costs/requirements.txt
costs/__init__.py
costs/__main__.py
costs/capital_costs.py
costs/configuration.py
costs/constants.py
costs/cost.py
costs/cost_base.py
costs/end_of_life_costs.py
costs/peak_load.py
costs/total_maintenance_costs.py
costs/total_operational_costs.py
costs/total_operational_incomes.py
costs/version.py
cerc_costs-0.1.0.6.dist-info/METADATA
cerc_costs-0.1.0.6.dist-info/WHEEL
cerc_costs-0.1.0.6.dist-info/top_level.txt
cerc_costs-0.1.0.6.dist-info/RECORD
